{
  "project_info": {
    "project_number": "597984556906",
    "project_id": "beeutify",
    "storage_bucket": "beeutify.firebasestorage.app"
  },
  "client": [
    {
      "client_info": {
        "mobilesdk_app_id": "1:597984556906:android:13e29185faf18df01f5713",
        "android_client_info": {
          "package_name": "com.shaadow.beeutify.client"
        }
      },
      "oauth_client": [],
      "api_key": [
        {
          "current_key": "AIzaSyCAZmOLhcOtTPlWimiLhPtZ2sv_n_e8FBQ"
        }
      ],
      "services": {
        "appinvite_service": {
          "other_platform_oauth_client": []
        }
      }
    }
  ],
  "configuration_version": "1"
}